{
  "topics" :
  [{
    "type": "kitties",
    "title": "Kitty!",
    "description": "This kitty is so cute.",
    "img": "http://cdn.attackofthecute.com/February-20-2012-20-58-35-catsncats.tumblr1.jpeg"
  },
  {
    "type": "cars",
    "title": "1968 Pontiac Firebird",
    "description": "Like this car needs a description",
    "img": "https://assets.hemmings.com/story_image/604653-1000-0@2x.jpg?rev=2"
  },
   {
    "type": "pastries",
    "title": "Go nuts for donuts!",
    "description": "I like donuts. A Lot.",
    "img": "https://s3-media2.fl.yelpcdn.com/bphoto/KxFdYhnvGMRbUVfaskhKww/348s.jpg"
  },
   {
    "type": "puppies",
    "title": "Puppy chases tail, finds self.",
    "description": "Cute and so, so zen.",
    "img": "https://s-media-cache-ak0.pinimg.com/736x/69/3a/dc/693adcc306fdacd7829852bf51f438c2.jpg"
  }]
}
